airnowpy/__init__.py
airnowpy/api.py
airnowpy/category.py
airnowpy/observation.py
airnowpy-2.3.2.dist-info/licenses/LICENSE
airnowpy-2.3.2.dist-info/METADATA
airnowpy-2.3.2.dist-info/WHEEL
airnowpy-2.3.2.dist-info/top_level.txt
airnowpy-2.3.2.dist-info/RECORD
