Metadata-Version: 2.4
Name: airnowpy
Version: 2.3.2
Summary: Python Library for the AirNow API
Home-page: https://github.com/karjanme/airnowpy
Author: Karl Jansen
Author-email: jnsnkrl@live.com
License: MIT
Classifier: Development Status :: 4 - Beta
Classifier: Intended Audience :: Developers
Classifier: Intended Audience :: Education
Classifier: Intended Audience :: Science/Research
Classifier: Programming Language :: Python :: 3
Classifier: License :: OSI Approved :: MIT License
Classifier: Operating System :: OS Independent
Classifier: Topic :: Scientific/Engineering :: Atmospheric Science
Classifier: Topic :: Software Development :: Libraries
License-File: LICENSE
Requires-Dist: pytz
Requires-Dist: requests
Dynamic: author
Dynamic: author-email
Dynamic: classifier
Dynamic: description
Dynamic: description-content-type
Dynamic: home-page
Dynamic: license
Dynamic: license-file
Dynamic: requires-dist
Dynamic: summary
